niimath/_dist_ver.py
niimath/__init__.py
niimath/__main__.py
niimath/bin/niimath
niimath-1.0.20250804.dist-info/RECORD
niimath-1.0.20250804.dist-info/WHEEL
niimath-1.0.20250804.dist-info/entry_points.txt
niimath-1.0.20250804.dist-info/METADATA
niimath-1.0.20250804.dist-info/licenses/LICENSE
