Metadata-Version: 2.1
Name: niimath
Version: 1.0.20250804
Summary: NIfTI arithmetic utilities
Keywords: research,neuroimaging,neuroscience,mri,nifti,dcm,nii,nitrc
Author: The niimath developers
Maintainer-Email: Casper da Costa-Luis <imaging@cdcl.ml>
License: BSD 2-Clause License
Classifier: Development Status :: 4 - Beta
Classifier: Intended Audience :: Science/Research
Classifier: Topic :: Scientific/Engineering :: Medical Science Apps.
Classifier: Programming Language :: Python :: 3
Classifier: License :: OSI Approved :: BSD License
Classifier: Operating System :: OS Independent
Project-URL: repository, https://github.com/rordenlab/niimath
Project-URL: changelog, https://github.com/rordenlab/niimath/releases
Requires-Python: >=3.7
